{
    "bundle": {
        "macOS": {
            "entitlements": "entitlements.plist",
            "hardenedRuntime": true,
            "exceptionDomain": "screenpi.pe",
            "provisioningProfile": null,
            "dmg": {
                "background": "assets/dmg-background.png"
            }
        },
        "externalBin": [
            "binaries/screenpipe",
            "binaries/bun",
            "ui_monitor",
            "binaries/ffmpeg",
            "binaries/ffprobe"
        ]
    }
}
